db_help_utils/__init__.py
db_help_utils/main.py
db_help_utils/test.py
db_help_utils-0.3.4.dist-info/METADATA
db_help_utils-0.3.4.dist-info/WHEEL
db_help_utils-0.3.4.dist-info/top_level.txt
db_help_utils-0.3.4.dist-info/RECORD
