Metadata-Version: 2.4
Name: db_help_utils
Version: 0.3.4
Summary: Утилиты для работы с базами данных
Home-page: https://github.com/paladinxb
Author: ilya
Author-email: asuslover4@gmail.com
License: MIT
Requires-Python: >=3.7
Dynamic: author
Dynamic: author-email
Dynamic: description
Dynamic: description-content-type
Dynamic: home-page
Dynamic: license
Dynamic: requires-python
Dynamic: summary
